evolution_api_client/__init__.py
evolution_api_client/api_client.py
evolution_api_client/api_response.py
evolution_api_client/configuration.py
evolution_api_client/exceptions.py
evolution_api_client/py.typed
evolution_api_client/rest.py
evolution_api_client/api/__init__.py
evolution_api_client/api/chama_ai_api.py
evolution_api_client/api/chat_controller_api.py
evolution_api_client/api/chatwoot_api.py
evolution_api_client/api/group_controller_api.py
evolution_api_client/api/instance_controller_api.py
evolution_api_client/api/jwt_api.py
evolution_api_client/api/label_controller_api.py
evolution_api_client/api/profile_settings_api.py
evolution_api_client/api/proxy_api.py
evolution_api_client/api/rabbit_mq_api.py
evolution_api_client/api/send_message_controller_api.py
evolution_api_client/api/settings_api.py
evolution_api_client/api/typebot_api.py
evolution_api_client/api/webhook_api.py
evolution_api_client/api/websocket_api.py
evolution_api_client/models/__init__.py
evolution_api_client/models/chamaai_set_instance_name_post_request.py
evolution_api_client/models/chat_archive_chat_instance_name_put_request.py
evolution_api_client/models/chat_archive_chat_instance_name_put_request_last_message.py
evolution_api_client/models/chat_archive_chat_instance_name_put_request_last_message_key.py
evolution_api_client/models/chat_fetch_business_profile_instance_name_post_request.py
evolution_api_client/models/chat_fetch_profile_picture_url_instance_name_post_request.py
evolution_api_client/models/chat_find_contacts_instance_name_post_request.py
evolution_api_client/models/chat_find_contacts_instance_name_post_request_where.py
evolution_api_client/models/chat_find_messages_instance_name_post_request.py
evolution_api_client/models/chat_find_messages_instance_name_post_request_where.py
evolution_api_client/models/chat_find_status_message_instance_name_post_request.py
evolution_api_client/models/chat_find_status_message_instance_name_post_request_where.py
cliente_evolution_api-0.1.0.dist-info/METADATA
cliente_evolution_api-0.1.0.dist-info/WHEEL
cliente_evolution_api-0.1.0.dist-info/top_level.txt
cliente_evolution_api-0.1.0.dist-info/RECORD
