Metadata-Version: 2.1
Name: cliente-evolution-api
Version: 0.1.0
Summary: Biblioteca Python para cliente da EvolutionAPI
Home-page: https://github.com/FlavioCoutinhoGO/evolution-api-client
Author: Flávio Coutinho
Author-email: coutinho.fg@gmail.com
License: MIT
Keywords: Evolution API,Evolution API Client,evolution-api-client
Platform: UNKNOWN
Classifier: License :: OSI Approved :: MIT License
Classifier: Programming Language :: Python :: 3
Classifier: Programming Language :: Python :: 3.9
Classifier: Programming Language :: Python :: 3.10
Classifier: Programming Language :: Python :: 3.11
Classifier: Programming Language :: Python :: 3.12
Classifier: Topic :: Software Development :: Libraries :: Python Modules
Classifier: Development Status :: 3 - Alpha
Classifier: Intended Audience :: Developers
Requires-Python: >=3.9
Requires-Dist: urllib3 <2.1.0,>=1.25.3
Requires-Dist: python-dateutil
Requires-Dist: pydantic >=2
Requires-Dist: typing-extensions >=4.7.1
